run_py/__init__.py
run_py/run_modules.py
run_py-3.0.0.dist-info/METADATA
run_py-3.0.0.dist-info/WHEEL
run_py-3.0.0.dist-info/RECORD
