Metadata-Version: 2.1
Name: run_py
Version: 3.0.0
Author-email: Mahdi Mir <imahdimir@gmail.com>
Requires-Dist: githubdata
